{"cameraMode":{"drawMode":0,"name":"Shaded","section":"Shading Mode"},"sceneLighting":true,"audioPlay":false,"sceneViewState":{"showFog":true,"showMaterialUpdate":false,"showSkybox":true,"showFlares":true,"showImageEffects":true,"showParticleSystems":true},"in2DMode":false,"pivot":{"x":1262.3704833984375,"y":557.6619873046875,"z":188.7811279296875},"rotation":{"x":-0.0003104317293036729,"y":-0.0024031633511185648,"z":7.682733098590688e-7,"w":-0.999997079372406},"size":1599.6307373046875,"orthographic":false}